finanfut_sdk/__init__.py
finanfut_sdk/_base.py
finanfut_sdk/access_tokens.py
finanfut_sdk/agents.py
finanfut_sdk/analytics.py
finanfut_sdk/applications.py
finanfut_sdk/auth.py
finanfut_sdk/billing.py
finanfut_sdk/cli.py
finanfut_sdk/client.py
finanfut_sdk/config.py
finanfut_sdk/contexts.py
finanfut_sdk/data_import.py
finanfut_sdk/documents.py
finanfut_sdk/intents.py
finanfut_sdk/interact.py
finanfut_sdk/memory.py
finanfut_sdk/requests.py
finanfut_sdk/utils/__init__.py
finanfut_sdk/utils/errors.py
finanfut_sdk/utils/logging.py
finanfut_sdk/utils/types.py
finanfut_sdk-1.0.2.dist-info/licenses/LICENSE
finanfut_sdk-1.0.2.dist-info/METADATA
finanfut_sdk-1.0.2.dist-info/WHEEL
finanfut_sdk-1.0.2.dist-info/entry_points.txt
finanfut_sdk-1.0.2.dist-info/top_level.txt
finanfut_sdk-1.0.2.dist-info/RECORD
