Metadata-Version: 2.4
Name: finanfut-sdk
Version: 1.0.2
Summary: Official FinanFut Intelligence Python SDK
Author-email: FinanFut <support@finanfut.com>
License: MIT License
Project-URL: Homepage, https://finanfut.com
Project-URL: Repository, https://github.com/<EL-TEU-REPO>
Project-URL: Documentation, https://finanfut.com/docs
Requires-Python: >=3.12
License-File: LICENSE
Requires-Dist: requests>=2.31.0
Requires-Dist: pydantic>=2.6
Requires-Dist: pydantic-settings>=2
Dynamic: license-file
